{
  "namespaces": [
    "public"
  ],
  "name": "public",
  "tables": [
    {
      "columns": {
        "id": {
          "name": "id",
          "type": "text",
          "unsigned": false,
          "autoincrement": false,
          "primary": false,
          "nullable": false,
          "mappedType": "text"
        },
        "user_id": {
          "name": "user_id",
          "type": "text",
          "unsigned": false,
          "autoincrement": false,
          "primary": false,
          "nullable": false,
          "mappedType": "text"
        },
        "bio": {
          "name": "bio",
          "type": "text",
          "unsigned": false,
          "autoincrement": false,
          "primary": false,
          "nullable": true,
          "mappedType": "text"
        },
        "portfolio_link": {
          "name": "portfolio_link",
          "type": "text",
          "unsigned": false,
          "autoincrement": false,
          "primary": false,
          "nullable": true,
          "mappedType": "text"
        },
        "is_verified": {
          "name": "is_verified",
          "type": "boolean",
          "unsigned": false,
          "autoincrement": false,
          "primary": false,
          "nullable": false,
          "default": "false",
          "mappedType": "boolean"
        },
        "created_at": {
          "name": "created_at",
          "type": "timestamptz",
          "unsigned": false,
          "autoincrement": false,
          "primary": false,
          "nullable": false,
          "length": 6,
          "default": "now()",
          "mappedType": "datetime"
        },
        "updated_at": {
          "name": "updated_at",
          "type": "timestamptz",
          "unsigned": false,
          "autoincrement": false,
          "primary": false,
          "nullable": false,
          "length": 6,
          "default": "now()",
          "mappedType": "datetime"
        },
        "deleted_at": {
          "name": "deleted_at",
          "type": "timestamptz",
          "unsigned": false,
          "autoincrement": false,
          "primary": false,
          "nullable": true,
          "length": 6,
          "mappedType": "datetime"
        }
      },
      "name": "designer",
      "schema": "public",
      "indexes": [
        {
          "keyName": "IDX_designer_user_id_unique",
          "columnNames": [],
          "composite": false,
          "constraint": false,
          "primary": false,
          "unique": false,
          "expression": "CREATE UNIQUE INDEX IF NOT EXISTS \"IDX_designer_user_id_unique\" ON \"designer\" (\"user_id\") WHERE deleted_at IS NULL"
        },
        {
          "keyName": "IDX_designer_deleted_at",
          "columnNames": [],
          "composite": false,
          "constraint": false,
          "primary": false,
          "unique": false,
          "expression": "CREATE INDEX IF NOT EXISTS \"IDX_designer_deleted_at\" ON \"designer\" (\"deleted_at\") WHERE deleted_at IS NULL"
        },
        {
          "keyName": "designer_pkey",
          "columnNames": [
            "id"
          ],
          "composite": false,
          "constraint": true,
          "primary": true,
          "unique": true
        }
      ],
      "checks": [],
      "foreignKeys": {},
      "nativeEnums": {}
    },
    {
      "columns": {
        "id": {
          "name": "id",
          "type": "text",
          "unsigned": false,
          "autoincrement": false,
          "primary": false,
          "nullable": false,
          "mappedType": "text"
        },
        "title": {
          "name": "title",
          "type": "text",
          "unsigned": false,
          "autoincrement": false,
          "primary": false,
          "nullable": false,
          "mappedType": "text"
        },
        "description": {
          "name": "description",
          "type": "text",
          "unsigned": false,
          "autoincrement": false,
          "primary": false,
          "nullable": true,
          "mappedType": "text"
        },
        "image_url": {
          "name": "image_url",
          "type": "text",
          "unsigned": false,
          "autoincrement": false,
          "primary": false,
          "nullable": false,
          "mappedType": "text"
        },
        "status": {
          "name": "status",
          "type": "text",
          "unsigned": false,
          "autoincrement": false,
          "primary": false,
          "nullable": false,
          "default": "'DRAFT'",
          "enumItems": [
            "DRAFT",
            "PENDING_REVIEW",
            "APPROVED",
            "REJECTED",
            "ARCHIVED"
          ],
          "mappedType": "enum"
        },
        "score": {
          "name": "score",
          "type": "integer",
          "unsigned": false,
          "autoincrement": false,
          "primary": false,
          "nullable": false,
          "default": "0",
          "mappedType": "integer"
        },
        "moderation_notes": {
          "name": "moderation_notes",
          "type": "text",
          "unsigned": false,
          "autoincrement": false,
          "primary": false,
          "nullable": true,
          "mappedType": "text"
        },
        "designer_id": {
          "name": "designer_id",
          "type": "text",
          "unsigned": false,
          "autoincrement": false,
          "primary": false,
          "nullable": false,
          "mappedType": "text"
        },
        "created_at": {
          "name": "created_at",
          "type": "timestamptz",
          "unsigned": false,
          "autoincrement": false,
          "primary": false,
          "nullable": false,
          "length": 6,
          "default": "now()",
          "mappedType": "datetime"
        },
        "updated_at": {
          "name": "updated_at",
          "type": "timestamptz",
          "unsigned": false,
          "autoincrement": false,
          "primary": false,
          "nullable": false,
          "length": 6,
          "default": "now()",
          "mappedType": "datetime"
        },
        "deleted_at": {
          "name": "deleted_at",
          "type": "timestamptz",
          "unsigned": false,
          "autoincrement": false,
          "primary": false,
          "nullable": true,
          "length": 6,
          "mappedType": "datetime"
        }
      },
      "name": "design",
      "schema": "public",
      "indexes": [
        {
          "keyName": "IDX_design_designer_id",
          "columnNames": [],
          "composite": false,
          "constraint": false,
          "primary": false,
          "unique": false,
          "expression": "CREATE INDEX IF NOT EXISTS \"IDX_design_designer_id\" ON \"design\" (\"designer_id\") WHERE deleted_at IS NULL"
        },
        {
          "keyName": "IDX_design_deleted_at",
          "columnNames": [],
          "composite": false,
          "constraint": false,
          "primary": false,
          "unique": false,
          "expression": "CREATE INDEX IF NOT EXISTS \"IDX_design_deleted_at\" ON \"design\" (\"deleted_at\") WHERE deleted_at IS NULL"
        },
        {
          "keyName": "design_pkey",
          "columnNames": [
            "id"
          ],
          "composite": false,
          "constraint": true,
          "primary": true,
          "unique": true
        }
      ],
      "checks": [],
      "foreignKeys": {
        "design_designer_id_foreign": {
          "constraintName": "design_designer_id_foreign",
          "columnNames": [
            "designer_id"
          ],
          "localTableName": "public.design",
          "referencedColumnNames": [
            "id"
          ],
          "referencedTableName": "public.designer",
          "updateRule": "cascade"
        }
      },
      "nativeEnums": {}
    }
  ],
  "nativeEnums": {}
}
